html2docx/__init__.py
html2docx/html2docx.py
html2docx/image-broken.png
html2docx/image.py
html2docx/py.typed
html2docx-1.6.0.dist-info/LICENSE
html2docx-1.6.0.dist-info/METADATA
html2docx-1.6.0.dist-info/WHEEL
html2docx-1.6.0.dist-info/top_level.txt
html2docx-1.6.0.dist-info/RECORD
