Metadata-Version: 2.1
Name: html2docx
Version: 1.6.0
Summary: Convert valid HTML input to docx.
Home-page: https://github.com/erezlife/html2docx
Author: eRezLife
Author-email: noreply@erezlife.com
Maintainer: eRezLife
Maintainer-email: noreply@erezlife.com
License: MIT
Classifier: Development Status :: 5 - Production/Stable
Classifier: Intended Audience :: Developers
Classifier: License :: OSI Approved :: MIT License
Classifier: Programming Language :: Python
Classifier: Programming Language :: Python :: 3
Classifier: Programming Language :: Python :: 3 :: Only
Classifier: Programming Language :: Python :: 3.7
Classifier: Programming Language :: Python :: 3.8
Classifier: Programming Language :: Python :: 3.9
Classifier: Programming Language :: Python :: 3.10
Classifier: Topic :: Software Development :: Libraries :: Python Modules
Classifier: Topic :: Utilities
Requires-Python: >=3.7
License-File: LICENSE
